fastimer/__init__.py
fastimer/__main__.py
fastimer/app.py
fastimer/constants.py
fastimer/datafile.py
fastimer/utils.py
fastimer-1.3.1.dist-info/LICENSE
fastimer-1.3.1.dist-info/METADATA
fastimer-1.3.1.dist-info/WHEEL
fastimer-1.3.1.dist-info/entry_points.txt
fastimer-1.3.1.dist-info/top_level.txt
fastimer-1.3.1.dist-info/RECORD
