Metadata-Version: 2.1
Name: fastimer
Version: 1.3.1
Summary: A simple CLI tool to track food you consume
Home-page: https://github.com/vkostyanetsky/Fastimer
Author: Vlad Kostyanetsky
Author-email: vlad@kostyanetsky.me
License: MIT
Keywords: fasting fast
Classifier: Development Status :: 5 - Production/Stable
Classifier: Environment :: Console
Classifier: Intended Audience :: End Users/Desktop
Classifier: License :: OSI Approved :: MIT License
Classifier: Operating System :: POSIX
Classifier: Programming Language :: Python :: 3.10
Classifier: Topic :: Utilities
Requires-Python: >=3.10
License-File: LICENSE
Requires-Dist: pyyaml ~=6.0.1
Requires-Dist: click ~=8.1.6
